headLineStyle/__init__.py
headLineStyle/tests.py
headline_style-1.5.7.dist-info/LICENSE
headline_style-1.5.7.dist-info/METADATA
headline_style-1.5.7.dist-info/WHEEL
headline_style-1.5.7.dist-info/top_level.txt
headline_style-1.5.7.dist-info/RECORD
